{
  "categories": [
    {
      "id": 1,
      "title": "JavaScript",
      "img": "https://res.cloudinary.com/do1zs5utw/image/upload/v1631222510/javascript_s199nx.png",
      "totalQuestions": 25
    },
    {
      "id": 2,
      "title": "PHP",
      "img": "https://res.cloudinary.com/do1zs5utw/image/upload/v1631222510/php_tenaqz.jpg",
      "totalQuestions": 10
    },
    {
      "id": 3,
      "title": "HTML",
      "img": "https://res.cloudinary.com/do1zs5utw/image/upload/v1631222510/html_hnl59u.jpg",
      "totalQuestions": 8
    },
    {
      "id": 4,
      "title": "Linux",
      "img": "",
      "totalQuestions": 10
    },
    {
      "id": 5,
      "title": "Docker",
      "img": "",
      "totalQuestions": 24
    },
    {
      "id": 6,
      "title": "MySQL",
      "img": "",
      "totalQuestions": 25
    },
    {
      "id": 7,
      "title": "Kubernetes",
      "img": "",
      "totalQuestions": 25
    },
    {
      "id": 8,
      "title": "Bash",
      "img": "",
      "totalQuestions": 35
    }
  ],
  "questions": [
    {
      "id": 509,
      "question": "<TD> … </TD> tag is used for ________",
      "answers": {
        "answer_a": "Table heading",
        "answer_b": "none of the above",
        "answer_c": "Table row",
        "answer_d": "Table Records",
        "answer_e": "sdfdsf",
        "answer_f": "asdasdasd"
      },
      "multiple_correct_answers": false,
      "correct_answers": {
        "answer_a_correct": false,
        "answer_b_correct": false,
        "answer_c_correct": false,
        "answer_d_correct": true,
        "answer_e_correct": false,
        "answer_f_correct": false
      },
      "correct_answer": "answer_a",
      "categoryId": 3
    },
    {
      "id": 535,
      "question": "Some tags enclose the text. Those tags are known as",
      "answers": {
        "answer_a": "Couple tags",
        "answer_b": "Pair tags",
        "answer_c": "Double tags",
        "answer_d": "Single tags",
        "answer_e": null,
        "answer_f": null
      },
      "multiple_correct_answers": false,
      "correct_answers": {
        "answer_a_correct": false,
        "answer_b_correct": true,
        "answer_c_correct": false,
        "answer_d_correct": false,
        "answer_e_correct": false,
        "answer_f_correct": false
      },
      "correct_answer": "answer_a",
      "categoryId": 3
    },
    {
      "id": 478,
      "question": "HTML are web pages read and rendered by",
      "answers": {
        "answer_a": "Compiler",
        "answer_b": "Interpreter",
        "answer_c": "Web Browser",
        "answer_d": "Server",
        "answer_e": null,
        "answer_f": null
      },
      "multiple_correct_answers": false,
      "correct_answers": {
        "answer_a_correct": false,
        "answer_b_correct": false,
        "answer_c_correct": true,
        "answer_d_correct": false,
        "answer_e_correct": false,
        "answer_f_correct": false
      },
      "correct_answer": "answer_a",
      "categoryId": 3
    },
    {
      "id": 456,
      "question": "Which attribute sets the text direction as related to lang attribute.",
      "answers": {
        "answer_a": "Sub",
        "answer_b": "Dir",
        "answer_c": "Ds",
        "answer_d": "Lang",
        "answer_e": null,
        "answer_f": null
      },
      "multiple_correct_answers": false,
      "correct_answers": {
        "answer_a_correct": false,
        "answer_b_correct": false,
        "answer_c_correct": false,
        "answer_d_correct": true,
        "answer_e_correct": false,
        "answer_f_correct": false
      },
      "correct_answer": "answer_a",
      "categoryId": 3
    },
    {
      "id": 488,
      "question": "HTML Uses",
      "answers": {
        "answer_a": "Fixed Tags Defined By The Language",
        "answer_b": "Pre-specified Tags",
        "answer_c": "Tags Only For Linking",
        "answer_d": "User Defined Tags",
        "answer_e": null,
        "answer_f": null
      },
      "multiple_correct_answers": false,
      "correct_answers": {
        "answer_a_correct": true,
        "answer_b_correct": false,
        "answer_c_correct": false,
        "answer_d_correct": false,
        "answer_e_correct": false,
        "answer_f_correct": false
      },
      "correct_answer": "answer_a",
      "categoryId": 3
    },
    {
      "id": 446,
      "question": "All HTML Tags must be enclosed In?",
      "answers": {
        "answer_a": "? And !",
        "answer_b": "# And #",
        "answer_c": "{ And }",
        "answer_d": "< And >",
        "answer_e": null,
        "answer_f": null
      },
      "multiple_correct_answers": false,
      "correct_answers": {
        "answer_a_correct": false,
        "answer_b_correct": false,
        "answer_c_correct": false,
        "answer_d_correct": true,
        "answer_e_correct": false,
        "answer_f_correct": false
      },
      "correct_answer": "answer_a",
      "categoryId": 3
    }
  ]
}